sslcommerz_client-0.6.0.dist-info/METADATA
sslcommerz_client-0.6.0.dist-info/WHEEL
sslcommerz_client-0.6.0.dist-info/licenses/AUTHORS.rst
sslcommerz_client-0.6.0.dist-info/licenses/LICENSE
sslcommerz_client/__init__.py
sslcommerz_client/client.py
sslcommerz_client/dataclasses.py
sslcommerz_client-0.6.0.dist-info/RECORD
