Metadata-Version: 2.1
Name: sslcommerz-client
Version: 0.6.0
Summary: A Sane SSLCommerz Client for Python.
Keywords: sslcommerz paymentgateway
Author-Email: Utsob Roy <roy@co.design>
License: MIT
Classifier: Development Status :: 5 - Production/Stable
Classifier: Intended Audience :: Developers
Classifier: License :: OSI Approved :: MIT License
Classifier: Operating System :: Unix
Classifier: Operating System :: POSIX
Classifier: Operating System :: Microsoft :: Windows
Classifier: Programming Language :: Python
Classifier: Programming Language :: Python :: 3
Classifier: Programming Language :: Python :: 3 :: Only
Classifier: Programming Language :: Python :: 3.6
Classifier: Programming Language :: Python :: 3.7
Classifier: Programming Language :: Python :: 3.8
Classifier: Programming Language :: Python :: 3.9
Classifier: Programming Language :: Python :: Implementation :: CPython
Classifier: Programming Language :: Python :: Implementation :: PyPy
Classifier: Topic :: Utilities
Project-URL: Documentation, https://python-sslcommerz-client.readthedocs.io/
Project-URL: Changelog, https://python-sslcommerz-client.readthedocs.io/en/latest/changelog.html
Project-URL: Issues, https://gitlab.com/codesigntheory/python-sslcommerz-client/issues
Requires-Python: >=3.9
Requires-Dist: pydantic>=2.6.4
Requires-Dist: requests>=2.31.0
Requires-Dist: sphinx-rtd-theme>=2.0.0; extra == "doc"
Requires-Dist: sphinx>=3; extra == "doc"
Provides-Extra: doc
